<annotation>
    <folder>vol</folder>
    <filename>1b1a64b0-4725-44bc-937e-12b13b3bc849.png</filename>
    <path>/vol/1b1a64b0-4725-44bc-937e-12b13b3bc849.png</path>
    <source>
        <database>Unknown</database>
    </source>
    <size>
        <width>1920</width>
        <height>1920</height>
        <depth>3</depth>
    </size>
    <segmented>0</segmented>
    <object>
        <name>Table Caption</name>
        <pose>Unspecified</pose>
        <truncated>0</truncated>
        <difficult>0</difficult>
        <bndbox>
            <xmin>136</xmin>
            <ymin>121</ymin>
            <xmax>1327</xmax>
            <ymax>173</ymax>
        </bndbox>
    </object>    <object>
        <name>Section Header</name>
        <pose>Unspecified</pose>
        <truncated>0</truncated>
        <difficult>0</difficult>
        <bndbox>
            <xmin>138</xmin>
            <ymin>1002</ymin>
            <xmax>418</xmax>
            <ymax>1036</ymax>
        </bndbox>
    </object>    <object>
        <name>Table</name>
        <pose>Unspecified</pose>
        <truncated>0</truncated>
        <difficult>0</difficult>
        <bndbox>
            <xmin>139</xmin>
            <ymin>176</ymin>
            <xmax>1331</xmax>
            <ymax>331</ymax>
        </bndbox>
    </object>    <object>
        <name>Body Text</name>
        <pose>Unspecified</pose>
        <truncated>0</truncated>
        <difficult>0</difficult>
        <bndbox>
            <xmin>139</xmin>
            <ymin>1049</ymin>
            <xmax>721</xmax>
            <ymax>1236</ymax>
        </bndbox>
    </object>    <object>
        <name>Body Text</name>
        <pose>Unspecified</pose>
        <truncated>0</truncated>
        <difficult>0</difficult>
        <bndbox>
            <xmin>140</xmin>
            <ymin>332</ymin>
            <xmax>1238</xmax>
            <ymax>372</ymax>
        </bndbox>
    </object>    <object>
        <name>Body Text</name>
        <pose>Unspecified</pose>
        <truncated>0</truncated>
        <difficult>0</difficult>
        <bndbox>
            <xmin>141</xmin>
            <ymin>429</ymin>
            <xmax>719</xmax>
            <ymax>928</ymax>
        </bndbox>
    </object>    <object>
        <name>Figure Caption</name>
        <pose>Unspecified</pose>
        <truncated>0</truncated>
        <difficult>0</difficult>
        <bndbox>
            <xmin>141</xmin>
            <ymin>1705</ymin>
            <xmax>719</xmax>
            <ymax>1785</ymax>
        </bndbox>
    </object>    <object>
        <name>Figure</name>
        <pose>Unspecified</pose>
        <truncated>0</truncated>
        <difficult>0</difficult>
        <bndbox>
            <xmin>167</xmin>
            <ymin>1282</ymin>
            <xmax>696</xmax>
            <ymax>1687</ymax>
        </bndbox>
    </object>    <object>
        <name>Body Text</name>
        <pose>Unspecified</pose>
        <truncated>0</truncated>
        <difficult>0</difficult>
        <bndbox>
            <xmin>749</xmin>
            <ymin>429</ymin>
            <xmax>1334</xmax>
            <ymax>1212</ymax>
        </bndbox>
    </object>    <object>
        <name>Body Text</name>
        <pose>Unspecified</pose>
        <truncated>0</truncated>
        <difficult>0</difficult>
        <bndbox>
            <xmin>752</xmin>
            <ymin>1348</ymin>
            <xmax>1334</xmax>
            <ymax>1787</ymax>
        </bndbox>
    </object>    <object>
        <name>Section Header</name>
        <pose>Unspecified</pose>
        <truncated>0</truncated>
        <difficult>0</difficult>
        <bndbox>
            <xmin>754</xmin>
            <ymin>1268</ymin>
            <xmax>1265</xmax>
            <ymax>1327</ymax>
        </bndbox>
    </object>    <object>
        <name>Page Header</name>
        <pose>Unspecified</pose>
        <truncated>0</truncated>
        <difficult>0</difficult>
        <bndbox>
            <xmin>998</xmin>
            <ymin>55</ymin>
            <xmax>1342</xmax>
            <ymax>93</ymax>
        </bndbox>
    </object>
</annotation>
