<annotation>
    <folder>vol</folder>
    <filename>294771c6-6b03-449b-a727-36ffd98bdedf.png</filename>
    <path>/vol/294771c6-6b03-449b-a727-36ffd98bdedf.png</path>
    <source>
        <database>Unknown</database>
    </source>
    <size>
        <width>1920</width>
        <height>1920</height>
        <depth>3</depth>
    </size>
    <segmented>0</segmented>
    <object>
        <name>Section Header</name>
        <pose>Unspecified</pose>
        <truncated>0</truncated>
        <difficult>0</difficult>
        <bndbox>
            <xmin>136</xmin>
            <ymin>1424</ymin>
            <xmax>674</xmax>
            <ymax>1487</ymax>
        </bndbox>
    </object>    <object>
        <name>Page Header</name>
        <pose>Unspecified</pose>
        <truncated>0</truncated>
        <difficult>0</difficult>
        <bndbox>
            <xmin>139</xmin>
            <ymin>60</ymin>
            <xmax>362</xmax>
            <ymax>88</ymax>
        </bndbox>
    </object>    <object>
        <name>Body Text</name>
        <pose>Unspecified</pose>
        <truncated>0</truncated>
        <difficult>0</difficult>
        <bndbox>
            <xmin>139</xmin>
            <ymin>124</ymin>
            <xmax>715</xmax>
            <ymax>1380</ymax>
        </bndbox>
    </object>    <object>
        <name>Body Text</name>
        <pose>Unspecified</pose>
        <truncated>0</truncated>
        <difficult>0</difficult>
        <bndbox>
            <xmin>139</xmin>
            <ymin>1503</ymin>
            <xmax>717</xmax>
            <ymax>1786</ymax>
        </bndbox>
    </object>    <object>
        <name>Body Text</name>
        <pose>Unspecified</pose>
        <truncated>0</truncated>
        <difficult>0</difficult>
        <bndbox>
            <xmin>751</xmin>
            <ymin>1760</ymin>
            <xmax>1142</xmax>
            <ymax>1778</ymax>
        </bndbox>
    </object>    <object>
        <name>Table Caption</name>
        <pose>Unspecified</pose>
        <truncated>0</truncated>
        <difficult>0</difficult>
        <bndbox>
            <xmin>752</xmin>
            <ymin>1512</ymin>
            <xmax>1333</xmax>
            <ymax>1595</ymax>
        </bndbox>
    </object>    <object>
        <name>Figure Caption</name>
        <pose>Unspecified</pose>
        <truncated>0</truncated>
        <difficult>0</difficult>
        <bndbox>
            <xmin>754</xmin>
            <ymin>540</ymin>
            <xmax>1332</xmax>
            <ymax>650</ymax>
        </bndbox>
    </object>    <object>
        <name>Body Text</name>
        <pose>Unspecified</pose>
        <truncated>0</truncated>
        <difficult>0</difficult>
        <bndbox>
            <xmin>755</xmin>
            <ymin>706</ymin>
            <xmax>1328</xmax>
            <ymax>1434</ymax>
        </bndbox>
    </object>    <object>
        <name>Figure</name>
        <pose>Unspecified</pose>
        <truncated>0</truncated>
        <difficult>0</difficult>
        <bndbox>
            <xmin>757</xmin>
            <ymin>124</ymin>
            <xmax>1324</xmax>
            <ymax>523</ymax>
        </bndbox>
    </object>    <object>
        <name>Table</name>
        <pose>Unspecified</pose>
        <truncated>0</truncated>
        <difficult>0</difficult>
        <bndbox>
            <xmin>759</xmin>
            <ymin>1597</ymin>
            <xmax>1329</xmax>
            <ymax>1753</ymax>
        </bndbox>
    </object>
</annotation>
