<annotation>
    <folder>vol</folder>
    <filename>37aa223e-e64b-4c78-9599-2ab5dcb7eed1.png</filename>
    <path>/vol/37aa223e-e64b-4c78-9599-2ab5dcb7eed1.png</path>
    <source>
        <database>Unknown</database>
    </source>
    <size>
        <width>1920</width>
        <height>1920</height>
        <depth>3</depth>
    </size>
    <segmented>0</segmented>
    <object>
        <name>Page Header</name>
        <pose>Unspecified</pose>
        <truncated>0</truncated>
        <difficult>0</difficult>
        <bndbox>
            <xmin>107</xmin>
            <ymin>119</ymin>
            <xmax>941</xmax>
            <ymax>147</ymax>
        </bndbox>
    </object>    <object>
        <name>Table Caption</name>
        <pose>Unspecified</pose>
        <truncated>0</truncated>
        <difficult>0</difficult>
        <bndbox>
            <xmin>110</xmin>
            <ymin>1228</ymin>
            <xmax>953</xmax>
            <ymax>1284</ymax>
        </bndbox>
    </object>    <object>
        <name>Table Caption</name>
        <pose>Unspecified</pose>
        <truncated>0</truncated>
        <difficult>0</difficult>
        <bndbox>
            <xmin>111</xmin>
            <ymin>172</ymin>
            <xmax>869</xmax>
            <ymax>222</ymax>
        </bndbox>
    </object>    <object>
        <name>Table Caption</name>
        <pose>Unspecified</pose>
        <truncated>0</truncated>
        <difficult>0</difficult>
        <bndbox>
            <xmin>111</xmin>
            <ymin>753</ymin>
            <xmax>732</xmax>
            <ymax>806</ymax>
        </bndbox>
    </object>    <object>
        <name>Table</name>
        <pose>Unspecified</pose>
        <truncated>0</truncated>
        <difficult>0</difficult>
        <bndbox>
            <xmin>113</xmin>
            <ymin>234</ymin>
            <xmax>1290</xmax>
            <ymax>609</ymax>
        </bndbox>
    </object>    <object>
        <name>Table</name>
        <pose>Unspecified</pose>
        <truncated>0</truncated>
        <difficult>0</difficult>
        <bndbox>
            <xmin>113</xmin>
            <ymin>813</ymin>
            <xmax>1293</xmax>
            <ymax>1167</ymax>
        </bndbox>
    </object>    <object>
        <name>Table</name>
        <pose>Unspecified</pose>
        <truncated>0</truncated>
        <difficult>0</difficult>
        <bndbox>
            <xmin>113</xmin>
            <ymin>1288</ymin>
            <xmax>1288</xmax>
            <ymax>1590</ymax>
        </bndbox>
    </object>    <object>
        <name>Body Text</name>
        <pose>Unspecified</pose>
        <truncated>0</truncated>
        <difficult>0</difficult>
        <bndbox>
            <xmin>113</xmin>
            <ymin>1641</ymin>
            <xmax>673</xmax>
            <ymax>1757</ymax>
        </bndbox>
    </object>    <object>
        <name>Body Text</name>
        <pose>Unspecified</pose>
        <truncated>0</truncated>
        <difficult>0</difficult>
        <bndbox>
            <xmin>128</xmin>
            <ymin>612</ymin>
            <xmax>604</xmax>
            <ymax>695</ymax>
        </bndbox>
    </object>    <object>
        <name>Body Text</name>
        <pose>Unspecified</pose>
        <truncated>0</truncated>
        <difficult>0</difficult>
        <bndbox>
            <xmin>726</xmin>
            <ymin>1639</ymin>
            <xmax>1293</xmax>
            <ymax>1758</ymax>
        </bndbox>
    </object>
</annotation>
