<annotation>
    <folder>vol</folder>
    <filename>55a6badc-0d2c-4778-8387-230dd6bb96a6.png</filename>
    <path>/vol/55a6badc-0d2c-4778-8387-230dd6bb96a6.png</path>
    <source>
        <database>Unknown</database>
    </source>
    <size>
        <width>1920</width>
        <height>1920</height>
        <depth>3</depth>
    </size>
    <segmented>0</segmented>
    <object>
        <name>Figure Caption</name>
        <pose>Unspecified</pose>
        <truncated>0</truncated>
        <difficult>0</difficult>
        <bndbox>
            <xmin>91</xmin>
            <ymin>1119</ymin>
            <xmax>1303</xmax>
            <ymax>1189</ymax>
        </bndbox>
    </object>    <object>
        <name>Body Text</name>
        <pose>Unspecified</pose>
        <truncated>0</truncated>
        <difficult>0</difficult>
        <bndbox>
            <xmin>91</xmin>
            <ymin>1272</ymin>
            <xmax>669</xmax>
            <ymax>1786</ymax>
        </bndbox>
    </object>    <object>
        <name>Figure</name>
        <pose>Unspecified</pose>
        <truncated>0</truncated>
        <difficult>0</difficult>
        <bndbox>
            <xmin>258</xmin>
            <ymin>128</ymin>
            <xmax>1141</xmax>
            <ymax>1094</ymax>
        </bndbox>
    </object>    <object>
        <name>Page Header</name>
        <pose>Unspecified</pose>
        <truncated>0</truncated>
        <difficult>0</difficult>
        <bndbox>
            <xmin>426</xmin>
            <ymin>83</ymin>
            <xmax>968</xmax>
            <ymax>112</ymax>
        </bndbox>
    </object>    <object>
        <name>Body Text</name>
        <pose>Unspecified</pose>
        <truncated>0</truncated>
        <difficult>0</difficult>
        <bndbox>
            <xmin>721</xmin>
            <ymin>1270</ymin>
            <xmax>1305</xmax>
            <ymax>1789</ymax>
        </bndbox>
    </object>    <object>
        <name>Page Header</name>
        <pose>Unspecified</pose>
        <truncated>0</truncated>
        <difficult>0</difficult>
        <bndbox>
            <xmin>1274</xmin>
            <ymin>82</ymin>
            <xmax>1303</xmax>
            <ymax>107</ymax>
        </bndbox>
    </object>
</annotation>
