<annotation>
    <folder>vol</folder>
    <filename>5aaf9393-4fbb-44af-8d4e-a4d1a75c53d7.png</filename>
    <path>/vol/5aaf9393-4fbb-44af-8d4e-a4d1a75c53d7.png</path>
    <source>
        <database>Unknown</database>
    </source>
    <size>
        <width>1920</width>
        <height>1920</height>
        <depth>3</depth>
    </size>
    <segmented>0</segmented>
    <object>
        <name>Page Footer</name>
        <pose>Unspecified</pose>
        <truncated>0</truncated>
        <difficult>0</difficult>
        <bndbox>
            <xmin>190</xmin>
            <ymin>1703</ymin>
            <xmax>259</xmax>
            <ymax>1746</ymax>
        </bndbox>
    </object>    <object>
        <name>Table Caption</name>
        <pose>Unspecified</pose>
        <truncated>0</truncated>
        <difficult>0</difficult>
        <bndbox>
            <xmin>204</xmin>
            <ymin>257</ymin>
            <xmax>237</xmax>
            <ymax>1682</ymax>
        </bndbox>
    </object>    <object>
        <name>Table</name>
        <pose>Unspecified</pose>
        <truncated>0</truncated>
        <difficult>0</difficult>
        <bndbox>
            <xmin>243</xmin>
            <ymin>213</ymin>
            <xmax>957</xmax>
            <ymax>1681</ymax>
        </bndbox>
    </object>    <object>
        <name>Body Text</name>
        <pose>Unspecified</pose>
        <truncated>0</truncated>
        <difficult>0</difficult>
        <bndbox>
            <xmin>962</xmin>
            <ymin>215</ymin>
            <xmax>1144</xmax>
            <ymax>1683</ymax>
        </bndbox>
    </object>
</annotation>
