<annotation>
    <folder>vol</folder>
    <filename>6532e3b4-8215-48c3-94f6-da3a43bdaf68.png</filename>
    <path>/vol/6532e3b4-8215-48c3-94f6-da3a43bdaf68.png</path>
    <source>
        <database>Unknown</database>
    </source>
    <size>
        <width>1920</width>
        <height>1920</height>
        <depth>3</depth>
    </size>
    <segmented>0</segmented>
    <object>
        <name>Section Header</name>
        <pose>Unspecified</pose>
        <truncated>0</truncated>
        <difficult>0</difficult>
        <bndbox>
            <xmin>93</xmin>
            <ymin>884</ymin>
            <xmax>610</xmax>
            <ymax>915</ymax>
        </bndbox>
    </object>    <object>
        <name>Section Header</name>
        <pose>Unspecified</pose>
        <truncated>0</truncated>
        <difficult>0</difficult>
        <bndbox>
            <xmin>96</xmin>
            <ymin>833</ymin>
            <xmax>351</xmax>
            <ymax>870</ymax>
        </bndbox>
    </object>    <object>
        <name>Body Text</name>
        <pose>Unspecified</pose>
        <truncated>0</truncated>
        <difficult>0</difficult>
        <bndbox>
            <xmin>96</xmin>
            <ymin>934</ymin>
            <xmax>712</xmax>
            <ymax>1799</ymax>
        </bndbox>
    </object>    <object>
        <name>Body Text</name>
        <pose>Unspecified</pose>
        <truncated>0</truncated>
        <difficult>0</difficult>
        <bndbox>
            <xmin>97</xmin>
            <ymin>156</ymin>
            <xmax>720</xmax>
            <ymax>795</ymax>
        </bndbox>
    </object>    <object>
        <name>Page Header</name>
        <pose>Unspecified</pose>
        <truncated>0</truncated>
        <difficult>0</difficult>
        <bndbox>
            <xmin>486</xmin>
            <ymin>104</ymin>
            <xmax>973</xmax>
            <ymax>139</ymax>
        </bndbox>
    </object>    <object>
        <name>Section Header</name>
        <pose>Unspecified</pose>
        <truncated>0</truncated>
        <difficult>0</difficult>
        <bndbox>
            <xmin>744</xmin>
            <ymin>378</ymin>
            <xmax>961</xmax>
            <ymax>409</ymax>
        </bndbox>
    </object>    <object>
        <name>Body Text</name>
        <pose>Unspecified</pose>
        <truncated>0</truncated>
        <difficult>0</difficult>
        <bndbox>
            <xmin>745</xmin>
            <ymin>430</ymin>
            <xmax>1365</xmax>
            <ymax>968</ymax>
        </bndbox>
    </object>    <object>
        <name>Body Text</name>
        <pose>Unspecified</pose>
        <truncated>0</truncated>
        <difficult>0</difficult>
        <bndbox>
            <xmin>746</xmin>
            <ymin>152</ymin>
            <xmax>1380</xmax>
            <ymax>359</ymax>
        </bndbox>
    </object>    <object>
        <name>Figure Caption</name>
        <pose>Unspecified</pose>
        <truncated>0</truncated>
        <difficult>0</difficult>
        <bndbox>
            <xmin>746</xmin>
            <ymin>1713</ymin>
            <xmax>1370</xmax>
            <ymax>1803</ymax>
        </bndbox>
    </object>    <object>
        <name>Figure</name>
        <pose>Unspecified</pose>
        <truncated>0</truncated>
        <difficult>0</difficult>
        <bndbox>
            <xmin>892</xmin>
            <ymin>994</ymin>
            <xmax>1212</xmax>
            <ymax>1701</ymax>
        </bndbox>
    </object>    <object>
        <name>Page Header</name>
        <pose>Unspecified</pose>
        <truncated>0</truncated>
        <difficult>0</difficult>
        <bndbox>
            <xmin>1317</xmin>
            <ymin>105</ymin>
            <xmax>1377</xmax>
            <ymax>135</ymax>
        </bndbox>
    </object>
</annotation>
