<annotation>
    <folder>vol</folder>
    <filename>7a18ecaa-6195-474c-a3fe-51e03c8ed54e.png</filename>
    <path>/vol/7a18ecaa-6195-474c-a3fe-51e03c8ed54e.png</path>
    <source>
        <database>Unknown</database>
    </source>
    <size>
        <width>1920</width>
        <height>1920</height>
        <depth>3</depth>
    </size>
    <segmented>0</segmented>
    <object>
        <name>Body Text</name>
        <pose>Unspecified</pose>
        <truncated>0</truncated>
        <difficult>0</difficult>
        <bndbox>
            <xmin>84</xmin>
            <ymin>72</ymin>
            <xmax>718</xmax>
            <ymax>1743</ymax>
        </bndbox>
    </object>    <object>
        <name>Page Footer</name>
        <pose>Unspecified</pose>
        <truncated>0</truncated>
        <difficult>0</difficult>
        <bndbox>
            <xmin>88</xmin>
            <ymin>1754</ymin>
            <xmax>1265</xmax>
            <ymax>1830</ymax>
        </bndbox>
    </object>    <object>
        <name>Body Text</name>
        <pose>Unspecified</pose>
        <truncated>0</truncated>
        <difficult>0</difficult>
        <bndbox>
            <xmin>727</xmin>
            <ymin>71</ymin>
            <xmax>1342</xmax>
            <ymax>162</ymax>
        </bndbox>
    </object>    <object>
        <name>Body Text</name>
        <pose>Unspecified</pose>
        <truncated>0</truncated>
        <difficult>0</difficult>
        <bndbox>
            <xmin>728</xmin>
            <ymin>259</ymin>
            <xmax>1359</xmax>
            <ymax>1756</ymax>
        </bndbox>
    </object>    <object>
        <name>Section Header</name>
        <pose>Unspecified</pose>
        <truncated>0</truncated>
        <difficult>0</difficult>
        <bndbox>
            <xmin>733</xmin>
            <ymin>198</ymin>
            <xmax>953</xmax>
            <ymax>249</ymax>
        </bndbox>
    </object>
</annotation>
