<annotation>
    <folder>vol</folder>
    <filename>9886674e-53e6-4659-9ec2-8e2347828e27.png</filename>
    <path>/vol/9886674e-53e6-4659-9ec2-8e2347828e27.png</path>
    <source>
        <database>Unknown</database>
    </source>
    <size>
        <width>1920</width>
        <height>1920</height>
        <depth>3</depth>
    </size>
    <segmented>0</segmented>
    <object>
        <name>Body Text</name>
        <pose>Unspecified</pose>
        <truncated>0</truncated>
        <difficult>0</difficult>
        <bndbox>
            <xmin>188</xmin>
            <ymin>199</ymin>
            <xmax>739</xmax>
            <ymax>1712</ymax>
        </bndbox>
    </object>    <object>
        <name>Page Header</name>
        <pose>Unspecified</pose>
        <truncated>0</truncated>
        <difficult>0</difficult>
        <bndbox>
            <xmin>194</xmin>
            <ymin>148</ymin>
            <xmax>496</xmax>
            <ymax>191</ymax>
        </bndbox>
    </object>    <object>
        <name>Page Footer</name>
        <pose>Unspecified</pose>
        <truncated>0</truncated>
        <difficult>0</difficult>
        <bndbox>
            <xmin>268</xmin>
            <ymin>1717</ymin>
            <xmax>1310</xmax>
            <ymax>1764</ymax>
        </bndbox>
    </object>    <object>
        <name>Body Text</name>
        <pose>Unspecified</pose>
        <truncated>0</truncated>
        <difficult>0</difficult>
        <bndbox>
            <xmin>757</xmin>
            <ymin>199</ymin>
            <xmax>1309</xmax>
            <ymax>1717</ymax>
        </bndbox>
    </object>
</annotation>
