<annotation>
    <folder>vol</folder>
    <filename>ae60a7a8-041c-4b4b-b572-f6995b95b327.png</filename>
    <path>/vol/ae60a7a8-041c-4b4b-b572-f6995b95b327.png</path>
    <source>
        <database>Unknown</database>
    </source>
    <size>
        <width>1920</width>
        <height>1920</height>
        <depth>3</depth>
    </size>
    <segmented>0</segmented>
    <object>
        <name>Body Text</name>
        <pose>Unspecified</pose>
        <truncated>0</truncated>
        <difficult>0</difficult>
        <bndbox>
            <xmin>72</xmin>
            <ymin>1195</ymin>
            <xmax>690</xmax>
            <ymax>1682</ymax>
        </bndbox>
    </object>    <object>
        <name>Page Header</name>
        <pose>Unspecified</pose>
        <truncated>0</truncated>
        <difficult>0</difficult>
        <bndbox>
            <xmin>73</xmin>
            <ymin>113</ymin>
            <xmax>120</xmax>
            <ymax>135</ymax>
        </bndbox>
    </object>    <object>
        <name>Figure Caption</name>
        <pose>Unspecified</pose>
        <truncated>0</truncated>
        <difficult>0</difficult>
        <bndbox>
            <xmin>73</xmin>
            <ymin>1000</ymin>
            <xmax>1338</xmax>
            <ymax>1127</ymax>
        </bndbox>
    </object>    <object>
        <name>Section Header</name>
        <pose>Unspecified</pose>
        <truncated>0</truncated>
        <difficult>0</difficult>
        <bndbox>
            <xmin>73</xmin>
            <ymin>1701</ymin>
            <xmax>304</xmax>
            <ymax>1728</ymax>
        </bndbox>
    </object>    <object>
        <name>Body Text</name>
        <pose>Unspecified</pose>
        <truncated>0</truncated>
        <difficult>0</difficult>
        <bndbox>
            <xmin>73</xmin>
            <ymin>1730</ymin>
            <xmax>689</xmax>
            <ymax>1831</ymax>
        </bndbox>
    </object>    <object>
        <name>Figure</name>
        <pose>Unspecified</pose>
        <truncated>0</truncated>
        <difficult>0</difficult>
        <bndbox>
            <xmin>102</xmin>
            <ymin>160</ymin>
            <xmax>1316</xmax>
            <ymax>984</ymax>
        </bndbox>
    </object>    <object>
        <name>Page Header</name>
        <pose>Unspecified</pose>
        <truncated>0</truncated>
        <difficult>0</difficult>
        <bndbox>
            <xmin>476</xmin>
            <ymin>110</ymin>
            <xmax>935</xmax>
            <ymax>133</ymax>
        </bndbox>
    </object>    <object>
        <name>Body Text</name>
        <pose>Unspecified</pose>
        <truncated>0</truncated>
        <difficult>0</difficult>
        <bndbox>
            <xmin>723</xmin>
            <ymin>1194</ymin>
            <xmax>1341</xmax>
            <ymax>1831</ymax>
        </bndbox>
    </object>
</annotation>
