<annotation>
    <folder>vol</folder>
    <filename>c5014e7e-0614-4c8e-a84b-98f39791dacd.png</filename>
    <path>/vol/c5014e7e-0614-4c8e-a84b-98f39791dacd.png</path>
    <source>
        <database>Unknown</database>
    </source>
    <size>
        <width>1920</width>
        <height>1920</height>
        <depth>3</depth>
    </size>
    <segmented>0</segmented>
    <object>
        <name>Reference text</name>
        <pose>Unspecified</pose>
        <truncated>0</truncated>
        <difficult>0</difficult>
        <bndbox>
            <xmin>91</xmin>
            <ymin>138</ymin>
            <xmax>718</xmax>
            <ymax>1634</ymax>
        </bndbox>
    </object>    <object>
        <name>Page Footer</name>
        <pose>Unspecified</pose>
        <truncated>0</truncated>
        <difficult>0</difficult>
        <bndbox>
            <xmin>96</xmin>
            <ymin>1828</ymin>
            <xmax>1367</xmax>
            <ymax>1895</ymax>
        </bndbox>
    </object>    <object>
        <name>Page Header</name>
        <pose>Unspecified</pose>
        <truncated>0</truncated>
        <difficult>0</difficult>
        <bndbox>
            <xmin>119</xmin>
            <ymin>9</ymin>
            <xmax>1362</xmax>
            <ymax>108</ymax>
        </bndbox>
    </object>    <object>
        <name>Reference text</name>
        <pose>Unspecified</pose>
        <truncated>0</truncated>
        <difficult>0</difficult>
        <bndbox>
            <xmin>750</xmin>
            <ymin>141</ymin>
            <xmax>1363</xmax>
            <ymax>1629</ymax>
        </bndbox>
    </object>
</annotation>
