<annotation>
    <folder>vol</folder>
    <filename>e5bd68da-37a9-47e4-9a21-5e7aaf93b4ac.png</filename>
    <path>/vol/e5bd68da-37a9-47e4-9a21-5e7aaf93b4ac.png</path>
    <source>
        <database>Unknown</database>
    </source>
    <size>
        <width>1920</width>
        <height>1920</height>
        <depth>3</depth>
    </size>
    <segmented>0</segmented>
    <object>
        <name>Body Text</name>
        <pose>Unspecified</pose>
        <truncated>0</truncated>
        <difficult>0</difficult>
        <bndbox>
            <xmin>93</xmin>
            <ymin>162</ymin>
            <xmax>715</xmax>
            <ymax>225</ymax>
        </bndbox>
    </object>    <object>
        <name>Body Text</name>
        <pose>Unspecified</pose>
        <truncated>0</truncated>
        <difficult>0</difficult>
        <bndbox>
            <xmin>93</xmin>
            <ymin>162</ymin>
            <xmax>715</xmax>
            <ymax>225</ymax>
        </bndbox>
    </object>    <object>
        <name>Body Text</name>
        <pose>Unspecified</pose>
        <truncated>0</truncated>
        <difficult>0</difficult>
        <bndbox>
            <xmin>94</xmin>
            <ymin>307</ymin>
            <xmax>716</xmax>
            <ymax>1062</ymax>
        </bndbox>
    </object>    <object>
        <name>Body Text</name>
        <pose>Unspecified</pose>
        <truncated>0</truncated>
        <difficult>0</difficult>
        <bndbox>
            <xmin>94</xmin>
            <ymin>307</ymin>
            <xmax>716</xmax>
            <ymax>1062</ymax>
        </bndbox>
    </object>    <object>
        <name>Section Header</name>
        <pose>Unspecified</pose>
        <truncated>0</truncated>
        <difficult>0</difficult>
        <bndbox>
            <xmin>95</xmin>
            <ymin>1468</ymin>
            <xmax>361</xmax>
            <ymax>1496</ymax>
        </bndbox>
    </object>    <object>
        <name>Section Header</name>
        <pose>Unspecified</pose>
        <truncated>0</truncated>
        <difficult>0</difficult>
        <bndbox>
            <xmin>95</xmin>
            <ymin>1468</ymin>
            <xmax>361</xmax>
            <ymax>1496</ymax>
        </bndbox>
    </object>    <object>
        <name>Section Header</name>
        <pose>Unspecified</pose>
        <truncated>0</truncated>
        <difficult>0</difficult>
        <bndbox>
            <xmin>97</xmin>
            <ymin>248</ymin>
            <xmax>430</xmax>
            <ymax>283</ymax>
        </bndbox>
    </object>    <object>
        <name>Section Header</name>
        <pose>Unspecified</pose>
        <truncated>0</truncated>
        <difficult>0</difficult>
        <bndbox>
            <xmin>97</xmin>
            <ymin>248</ymin>
            <xmax>430</xmax>
            <ymax>283</ymax>
        </bndbox>
    </object>    <object>
        <name>Section Header</name>
        <pose>Unspecified</pose>
        <truncated>0</truncated>
        <difficult>0</difficult>
        <bndbox>
            <xmin>97</xmin>
            <ymin>1404</ymin>
            <xmax>467</xmax>
            <ymax>1437</ymax>
        </bndbox>
    </object>    <object>
        <name>Section Header</name>
        <pose>Unspecified</pose>
        <truncated>0</truncated>
        <difficult>0</difficult>
        <bndbox>
            <xmin>97</xmin>
            <ymin>1404</ymin>
            <xmax>467</xmax>
            <ymax>1437</ymax>
        </bndbox>
    </object>    <object>
        <name>Body Text</name>
        <pose>Unspecified</pose>
        <truncated>0</truncated>
        <difficult>0</difficult>
        <bndbox>
            <xmin>98</xmin>
            <ymin>1149</ymin>
            <xmax>712</xmax>
            <ymax>1377</ymax>
        </bndbox>
    </object>    <object>
        <name>Body Text</name>
        <pose>Unspecified</pose>
        <truncated>0</truncated>
        <difficult>0</difficult>
        <bndbox>
            <xmin>98</xmin>
            <ymin>1149</ymin>
            <xmax>712</xmax>
            <ymax>1377</ymax>
        </bndbox>
    </object>    <object>
        <name>Body Text</name>
        <pose>Unspecified</pose>
        <truncated>0</truncated>
        <difficult>0</difficult>
        <bndbox>
            <xmin>98</xmin>
            <ymin>1518</ymin>
            <xmax>715</xmax>
            <ymax>1611</ymax>
        </bndbox>
    </object>    <object>
        <name>Body Text</name>
        <pose>Unspecified</pose>
        <truncated>0</truncated>
        <difficult>0</difficult>
        <bndbox>
            <xmin>98</xmin>
            <ymin>1518</ymin>
            <xmax>715</xmax>
            <ymax>1611</ymax>
        </bndbox>
    </object>    <object>
        <name>Section Header</name>
        <pose>Unspecified</pose>
        <truncated>0</truncated>
        <difficult>0</difficult>
        <bndbox>
            <xmin>100</xmin>
            <ymin>1087</ymin>
            <xmax>302</xmax>
            <ymax>1122</ymax>
        </bndbox>
    </object>    <object>
        <name>Section Header</name>
        <pose>Unspecified</pose>
        <truncated>0</truncated>
        <difficult>0</difficult>
        <bndbox>
            <xmin>100</xmin>
            <ymin>1087</ymin>
            <xmax>302</xmax>
            <ymax>1122</ymax>
        </bndbox>
    </object>    <object>
        <name>Body Text</name>
        <pose>Unspecified</pose>
        <truncated>0</truncated>
        <difficult>0</difficult>
        <bndbox>
            <xmin>100</xmin>
            <ymin>1716</ymin>
            <xmax>717</xmax>
            <ymax>1811</ymax>
        </bndbox>
    </object>    <object>
        <name>Body Text</name>
        <pose>Unspecified</pose>
        <truncated>0</truncated>
        <difficult>0</difficult>
        <bndbox>
            <xmin>100</xmin>
            <ymin>1716</ymin>
            <xmax>717</xmax>
            <ymax>1811</ymax>
        </bndbox>
    </object>    <object>
        <name>Page Header</name>
        <pose>Unspecified</pose>
        <truncated>0</truncated>
        <difficult>0</difficult>
        <bndbox>
            <xmin>462</xmin>
            <ymin>106</ymin>
            <xmax>1365</xmax>
            <ymax>137</ymax>
        </bndbox>
    </object>    <object>
        <name>Page Header</name>
        <pose>Unspecified</pose>
        <truncated>0</truncated>
        <difficult>0</difficult>
        <bndbox>
            <xmin>462</xmin>
            <ymin>106</ymin>
            <xmax>1365</xmax>
            <ymax>137</ymax>
        </bndbox>
    </object>    <object>
        <name>Body Text</name>
        <pose>Unspecified</pose>
        <truncated>0</truncated>
        <difficult>0</difficult>
        <bndbox>
            <xmin>747</xmin>
            <ymin>772</ymin>
            <xmax>1362</xmax>
            <ymax>1092</ymax>
        </bndbox>
    </object>    <object>
        <name>Body Text</name>
        <pose>Unspecified</pose>
        <truncated>0</truncated>
        <difficult>0</difficult>
        <bndbox>
            <xmin>747</xmin>
            <ymin>773</ymin>
            <xmax>1367</xmax>
            <ymax>857</ymax>
        </bndbox>
    </object>    <object>
        <name>Body Text</name>
        <pose>Unspecified</pose>
        <truncated>0</truncated>
        <difficult>0</difficult>
        <bndbox>
            <xmin>747</xmin>
            <ymin>889</ymin>
            <xmax>1362</xmax>
            <ymax>1092</ymax>
        </bndbox>
    </object>    <object>
        <name>Body Text</name>
        <pose>Unspecified</pose>
        <truncated>0</truncated>
        <difficult>0</difficult>
        <bndbox>
            <xmin>748</xmin>
            <ymin>447</ymin>
            <xmax>1370</xmax>
            <ymax>544</ymax>
        </bndbox>
    </object>    <object>
        <name>Body Text</name>
        <pose>Unspecified</pose>
        <truncated>0</truncated>
        <difficult>0</difficult>
        <bndbox>
            <xmin>748</xmin>
            <ymin>447</ymin>
            <xmax>1370</xmax>
            <ymax>544</ymax>
        </bndbox>
    </object>    <object>
        <name>Body Text</name>
        <pose>Unspecified</pose>
        <truncated>0</truncated>
        <difficult>0</difficult>
        <bndbox>
            <xmin>749</xmin>
            <ymin>160</ymin>
            <xmax>1360</xmax>
            <ymax>399</ymax>
        </bndbox>
    </object>    <object>
        <name>Body Text</name>
        <pose>Unspecified</pose>
        <truncated>0</truncated>
        <difficult>0</difficult>
        <bndbox>
            <xmin>749</xmin>
            <ymin>283</ymin>
            <xmax>1360</xmax>
            <ymax>399</ymax>
        </bndbox>
    </object>    <object>
        <name>Body Text</name>
        <pose>Unspecified</pose>
        <truncated>0</truncated>
        <difficult>0</difficult>
        <bndbox>
            <xmin>749</xmin>
            <ymin>626</ymin>
            <xmax>1370</xmax>
            <ymax>720</ymax>
        </bndbox>
    </object>    <object>
        <name>Body Text</name>
        <pose>Unspecified</pose>
        <truncated>0</truncated>
        <difficult>0</difficult>
        <bndbox>
            <xmin>749</xmin>
            <ymin>626</ymin>
            <xmax>1370</xmax>
            <ymax>720</ymax>
        </bndbox>
    </object>    <object>
        <name>Body Text</name>
        <pose>Unspecified</pose>
        <truncated>0</truncated>
        <difficult>0</difficult>
        <bndbox>
            <xmin>749</xmin>
            <ymin>1238</ymin>
            <xmax>1366</xmax>
            <ymax>1386</ymax>
        </bndbox>
    </object>    <object>
        <name>Body Text</name>
        <pose>Unspecified</pose>
        <truncated>0</truncated>
        <difficult>0</difficult>
        <bndbox>
            <xmin>749</xmin>
            <ymin>1238</ymin>
            <xmax>1366</xmax>
            <ymax>1386</ymax>
        </bndbox>
    </object>    <object>
        <name>Body Text</name>
        <pose>Unspecified</pose>
        <truncated>0</truncated>
        <difficult>0</difficult>
        <bndbox>
            <xmin>749</xmin>
            <ymin>1439</ymin>
            <xmax>1367</xmax>
            <ymax>1617</ymax>
        </bndbox>
    </object>    <object>
        <name>Body Text</name>
        <pose>Unspecified</pose>
        <truncated>0</truncated>
        <difficult>0</difficult>
        <bndbox>
            <xmin>749</xmin>
            <ymin>1445</ymin>
            <xmax>1365</xmax>
            <ymax>1531</ymax>
        </bndbox>
    </object>    <object>
        <name>Body Text</name>
        <pose>Unspecified</pose>
        <truncated>0</truncated>
        <difficult>0</difficult>
        <bndbox>
            <xmin>749</xmin>
            <ymin>1563</ymin>
            <xmax>1367</xmax>
            <ymax>1618</ymax>
        </bndbox>
    </object>    <object>
        <name>Body Text</name>
        <pose>Unspecified</pose>
        <truncated>0</truncated>
        <difficult>0</difficult>
        <bndbox>
            <xmin>753</xmin>
            <ymin>164</ymin>
            <xmax>1364</xmax>
            <ymax>248</ymax>
        </bndbox>
    </object>    <object>
        <name>Body Text</name>
        <pose>Unspecified</pose>
        <truncated>0</truncated>
        <difficult>0</difficult>
        <bndbox>
            <xmin>753</xmin>
            <ymin>1695</ymin>
            <xmax>1367</xmax>
            <ymax>1813</ymax>
        </bndbox>
    </object>    <object>
        <name>Body Text</name>
        <pose>Unspecified</pose>
        <truncated>0</truncated>
        <difficult>0</difficult>
        <bndbox>
            <xmin>753</xmin>
            <ymin>1695</ymin>
            <xmax>1367</xmax>
            <ymax>1813</ymax>
        </bndbox>
    </object>    <object>
        <name>Section Header</name>
        <pose>Unspecified</pose>
        <truncated>0</truncated>
        <difficult>0</difficult>
        <bndbox>
            <xmin>781</xmin>
            <ymin>860</ymin>
            <xmax>1130</xmax>
            <ymax>887</ymax>
        </bndbox>
    </object>    <object>
        <name>Section Header</name>
        <pose>Unspecified</pose>
        <truncated>0</truncated>
        <difficult>0</difficult>
        <bndbox>
            <xmin>781</xmin>
            <ymin>1534</ymin>
            <xmax>1048</xmax>
            <ymax>1561</ymax>
        </bndbox>
    </object>    <object>
        <name>Section Header</name>
        <pose>Unspecified</pose>
        <truncated>0</truncated>
        <difficult>0</difficult>
        <bndbox>
            <xmin>782</xmin>
            <ymin>250</ymin>
            <xmax>1152</xmax>
            <ymax>280</ymax>
        </bndbox>
    </object>    <object>
        <name>Equation</name>
        <pose>Unspecified</pose>
        <truncated>0</truncated>
        <difficult>0</difficult>
        <bndbox>
            <xmin>101</xmin>
            <ymin>1630</ymin>
            <xmax>714</xmax>
            <ymax>1705</ymax>
        </bndbox>
    </object>    <object>
        <name>Equation</name>
        <pose>Unspecified</pose>
        <truncated>0</truncated>
        <difficult>0</difficult>
        <bndbox>
            <xmin>751</xmin>
            <ymin>551</ymin>
            <xmax>1368</xmax>
            <ymax>619</ymax>
        </bndbox>
    </object>    <object>
        <name>Equation</name>
        <pose>Unspecified</pose>
        <truncated>0</truncated>
        <difficult>0</difficult>
        <bndbox>
            <xmin>751</xmin>
            <ymin>1625</ymin>
            <xmax>1363</xmax>
            <ymax>1689</ymax>
        </bndbox>
    </object>    <object>
        <name>Equation</name>
        <pose>Unspecified</pose>
        <truncated>0</truncated>
        <difficult>0</difficult>
        <bndbox>
            <xmin>747</xmin>
            <ymin>403</ymin>
            <xmax>1366</xmax>
            <ymax>445</ymax>
        </bndbox>
    </object>    <object>
        <name>Equation</name>
        <pose>Unspecified</pose>
        <truncated>0</truncated>
        <difficult>0</difficult>
        <bndbox>
            <xmin>747</xmin>
            <ymin>722</ymin>
            <xmax>1366</xmax>
            <ymax>769</ymax>
        </bndbox>
    </object>    <object>
        <name>Equation</name>
        <pose>Unspecified</pose>
        <truncated>0</truncated>
        <difficult>0</difficult>
        <bndbox>
            <xmin>749</xmin>
            <ymin>1395</ymin>
            <xmax>1366</xmax>
            <ymax>1435</ymax>
        </bndbox>
    </object>    <object>
        <name>Equation</name>
        <pose>Unspecified</pose>
        <truncated>0</truncated>
        <difficult>0</difficult>
        <bndbox>
            <xmin>751</xmin>
            <ymin>1186</ymin>
            <xmax>1362</xmax>
            <ymax>1235</ymax>
        </bndbox>
    </object>    <object>
        <name>Equation</name>
        <pose>Unspecified</pose>
        <truncated>0</truncated>
        <difficult>0</difficult>
        <bndbox>
            <xmin>751</xmin>
            <ymin>1095</ymin>
            <xmax>1363</xmax>
            <ymax>1143</ymax>
        </bndbox>
    </object>
</annotation>
