<annotation>
    <folder>vol</folder>
    <filename>fe92785b-80a5-4767-8faa-6eb5befc6edc.png</filename>
    <path>/vol/fe92785b-80a5-4767-8faa-6eb5befc6edc.png</path>
    <source>
        <database>Unknown</database>
    </source>
    <size>
        <width>1920</width>
        <height>1920</height>
        <depth>3</depth>
    </size>
    <segmented>0</segmented>
    <object>
        <name>Page Header</name>
        <pose>Unspecified</pose>
        <truncated>0</truncated>
        <difficult>0</difficult>
        <bndbox>
            <xmin>40</xmin>
            <ymin>35</ymin>
            <xmax>1416</xmax>
            <ymax>350</ymax>
        </bndbox>
    </object>    <object>
        <name>Other</name>
        <pose>Unspecified</pose>
        <truncated>0</truncated>
        <difficult>0</difficult>
        <bndbox>
            <xmin>211</xmin>
            <ymin>668</ymin>
            <xmax>1234</xmax>
            <ymax>765</ymax>
        </bndbox>
    </object>    <object>
        <name>Body Text</name>
        <pose>Unspecified</pose>
        <truncated>0</truncated>
        <difficult>0</difficult>
        <bndbox>
            <xmin>215</xmin>
            <ymin>583</ymin>
            <xmax>989</xmax>
            <ymax>624</ymax>
        </bndbox>
    </object>    <object>
        <name>Other</name>
        <pose>Unspecified</pose>
        <truncated>0</truncated>
        <difficult>0</difficult>
        <bndbox>
            <xmin>215</xmin>
            <ymin>769</ymin>
            <xmax>1000</xmax>
            <ymax>812</ymax>
        </bndbox>
    </object>    <object>
        <name>Section Header</name>
        <pose>Unspecified</pose>
        <truncated>0</truncated>
        <difficult>0</difficult>
        <bndbox>
            <xmin>217</xmin>
            <ymin>389</ymin>
            <xmax>1105</xmax>
            <ymax>539</ymax>
        </bndbox>
    </object>    <object>
        <name>Other</name>
        <pose>Unspecified</pose>
        <truncated>0</truncated>
        <difficult>0</difficult>
        <bndbox>
            <xmin>221</xmin>
            <ymin>1085</ymin>
            <xmax>470</xmax>
            <ymax>1141</ymax>
        </bndbox>
    </object>    <object>
        <name>Other</name>
        <pose>Unspecified</pose>
        <truncated>0</truncated>
        <difficult>0</difficult>
        <bndbox>
            <xmin>221</xmin>
            <ymin>1185</ymin>
            <xmax>539</xmax>
            <ymax>1250</ymax>
        </bndbox>
    </object>    <object>
        <name>Other</name>
        <pose>Unspecified</pose>
        <truncated>0</truncated>
        <difficult>0</difficult>
        <bndbox>
            <xmin>225</xmin>
            <ymin>1291</ymin>
            <xmax>547</xmax>
            <ymax>1352</ymax>
        </bndbox>
    </object>    <object>
        <name>Other</name>
        <pose>Unspecified</pose>
        <truncated>0</truncated>
        <difficult>0</difficult>
        <bndbox>
            <xmin>230</xmin>
            <ymin>886</ymin>
            <xmax>607</xmax>
            <ymax>958</ymax>
        </bndbox>
    </object>    <object>
        <name>Other</name>
        <pose>Unspecified</pose>
        <truncated>0</truncated>
        <difficult>0</difficult>
        <bndbox>
            <xmin>232</xmin>
            <ymin>989</ymin>
            <xmax>665</xmax>
            <ymax>1050</ymax>
        </bndbox>
    </object>
</annotation>
